paraping/__init__.py
paraping/main.py
paraping-0.0.1.dist-info/METADATA
paraping-0.0.1.dist-info/WHEEL
paraping-0.0.1.dist-info/top_level.txt
paraping-0.0.1.dist-info/RECORD
