Metadata-Version: 2.1
Name: paraping
Version: 0.0.1
Requires-Dist: ip-address ==1.5.0
